yunopyutils/__init__.py
yunopyutils/logger/create_log.py
yunopyutils-1.0.0a2.dist-info/METADATA
yunopyutils-1.0.0a2.dist-info/WHEEL
yunopyutils-1.0.0a2.dist-info/RECORD
