Metadata-Version: 2.1
Name: yunopyutils
Version: 1.0.0a2
Summary: Utils for python
Project-URL: Homepage, https://github.com/yuno-payments/yuno-py-utils
Author-email: yunopayments <utils-tech@y.uno>
License: MIT
Requires-Python: >=3.9
Requires-Dist: python-dotenv>=1.0.0
